smooch_logs/__init__.py
smooch_logs/downloader.py
smooch_logs/session.py
smooch_logs-0.1.8.dist-info/LICENSE
smooch_logs-0.1.8.dist-info/METADATA
smooch_logs-0.1.8.dist-info/WHEEL
smooch_logs-0.1.8.dist-info/top_level.txt
smooch_logs-0.1.8.dist-info/RECORD
