Metadata-Version: 2.1
Name: smooch-logs
Version: 0.1.8
Summary: Simple module for downloading Smooch logs from their website.
Home-page: https://github.com/fivehealth/smooch-logs
Author: 5 Health Inc
Author-email: hello@botmd.io
License: MIT License
Keywords: selenium smooch
Platform: UNKNOWN
Classifier: Development Status :: 4 - Beta
Classifier: Programming Language :: Python :: 3
Classifier: License :: OSI Approved :: MIT License
Requires-Python: >=3.6
Requires-Dist: selenium
Requires-Dist: python-dateutil
Requires-Dist: pytz
Requires-Dist: webdriver-manager
Requires-Dist: requests
Requires-Dist: uriutils
